AutoGAN/__init__.py
AutoGAN/schemes/ACGAN_TrainingScheme.py
AutoGAN/schemes/Base_TrainingScheme.py
AutoGAN/schemes/ContentGAN_TrainingScheme.py
AutoGAN/schemes/CycleGAN_TrainingScheme.py
AutoGAN/schemes/IWGAN_TrainingScheme.py
AutoGAN/schemes/SimGAN_TrainingScheme.py
AutoGAN/schemes/__init__.py
AutoGAN/utils/__init__.py
AutoGAN/utils/gan_utils.py
AutoGAN-0.0.5.dist-info/DESCRIPTION.rst
AutoGAN-0.0.5.dist-info/LICENSE.txt
AutoGAN-0.0.5.dist-info/METADATA
AutoGAN-0.0.5.dist-info/RECORD
AutoGAN-0.0.5.dist-info/WHEEL
AutoGAN-0.0.5.dist-info/metadata.json
AutoGAN-0.0.5.dist-info/top_level.txt
