Metadata-Version: 2.0
Name: AutoGAN
Version: 0.0.5
Summary: GANs were never easier
Home-page: http://github.com/EladDv/AutoGAN_Test
Author: Elad Dvash
Author-email: UNKNOWN
License: MIT
Keywords: keras gan gans ai
Platform: UNKNOWN
Classifier: Development Status :: 3 - Alpha
Classifier: License :: OSI Approved :: MIT License
Classifier: Programming Language :: Python :: 2
Classifier: Programming Language :: Python :: 2.7
Classifier: Programming Language :: Python :: 3
Classifier: Programming Language :: Python :: 3.6
Classifier: Topic :: Software Development :: Libraries
Classifier: Topic :: Software Development :: Libraries :: Python Modules
Classifier: Intended Audience :: Developers
Classifier: Intended Audience :: Education
Classifier: Intended Audience :: Science/Research
Requires-Dist: keras (>=2)
Requires-Dist: tensorflow (<=1.13)
